examples/__init__.py
examples/UQ/__init__.py
examples/UQ/finite_dimensional.py
examples/UQ/kl1D_example.py
examples/UQ/kl_example.py
examples/UQ/poisson_example.py
examples/kink/H1convergence.py
examples/kink/__init__.py
examples/kink/main.py
examples/particle_systems/__init__.py
examples/particle_systems/experiment.py
examples/particle_systems/particle_systems.py
examples/unbounded_integration/__init__.py
smolyak/__init__.py
smolyak/indices.py
smolyak/smolyak.py
smolyak/applications/__init__.py
smolyak/applications/particle_systems/__init__.py
smolyak/applications/particle_systems/optimal_control.py
smolyak/applications/particle_systems/particle_approximations.py
smolyak/applications/particle_systems/value_functions.py
smolyak/applications/pde/__init__.py
smolyak/applications/pde/kl.py
smolyak/applications/pde/kl1D.py
smolyak/applications/pde/poisson.py
smolyak/applications/polynomials/__init__.py
smolyak/applications/polynomials/orthogonal_polynomials.py
smolyak/applications/polynomials/polynomial_approximation.py
smolyak/applications/polynomials/probability_distributions.py
smolyak/applications/polynomials/samples.py
smolyak-2.6.7.dist-info/LICENSE
smolyak-2.6.7.dist-info/METADATA
smolyak-2.6.7.dist-info/WHEEL
smolyak-2.6.7.dist-info/top_level.txt
smolyak-2.6.7.dist-info/RECORD
