Metadata-Version: 2.1
Name: smolyak
Version: 2.6.7
Summary: Accelerate scientific computations using Smolyak's algorithm
Home-page: https://github.com/soerenwolfers/smolyak
Author: Soeren Wolfers
Author-email: soeren.wolfers@gmail.com
License: UNKNOWN
Platform: UNKNOWN
Requires-Python: >=3.6
Requires-Dist: numpy
Requires-Dist: scipy
Requires-Dist: swutil
